pyRing/NR_amp.py
pyRing/__init__.py
pyRing/eob_utils.c
pyRing/eob_utils.cpython-37m-darwin.so
pyRing/eob_utils.pxd
pyRing/eob_utils.pyx
pyRing/initialise.py
pyRing/inject_signal.py
pyRing/likelihood.c
pyRing/likelihood.cpython-37m-darwin.so
pyRing/likelihood.pyx
pyRing/noise.py
pyRing/plots.py
pyRing/pyRing.py
pyRing/utils.py
pyRing/waveform.c
pyRing/waveform.cpython-37m-darwin.so
pyRing/waveform.pxd
pyRing/waveform.pyx
pyRing/config_files/config_KN_inj.ini
pyRing/config_files/config_LAL_inj.ini
pyRing/config_files/config_NR_inj.ini
pyRing/config_files/config_TEOBPM_inj.ini
pyRing/config_files/config_damped_sinusoids_inj_detector_noise.ini
pyRing/config_files/config_damped_sinusoids_inj_gaussian_noise.ini
pyRing/config_files/config_gw150914.ini
pyRing/config_files/config_gw150914_ParSpec.ini
pyRing/config_files/config_gw150914_TEOBPM.ini
pyRing/config_files/config_gw150914_braneworld.ini
pyRing/config_files/config_gw150914_charge.ini
pyRing/config_files/config_gw150914_local_data.ini
pyRing/config_files/config_gw150914_local_data_raynest.ini
pyRing/config_files/config_gw150914_non_tensorial.ini
pyRing/config_files/config_gw150914_production.ini
pyRing/config_files/config_kerr_ParSpec_inj.ini
pyRing/config_files/config_kerr_braneworld_inj.ini
pyRing/config_files/config_kerr_inj.ini
pyRing/config_files/config_kerr_nonGR_inj.ini
pyRing/config_files/config_kerr_quadratic_inj.ini
pyRing/config_files/config_kerr_tail_inj.ini
pyRing/config_files/config_mmrdnp_inj.ini
pyRing/config_files/config_mmrdns_inj.ini
pyRing/config_files/config_morlet_gabor_wavelets.ini
pyRing/config_files/Quickstart_configs/README.md
pyRing/config_files/Quickstart_configs/quick_gw150914_DS.ini
pyRing/config_files/Quickstart_configs/quick_gw150914_KN.ini
pyRing/config_files/Quickstart_configs/quick_gw150914_Kerr_220.ini
pyRing/config_files/Quickstart_configs/quick_gw150914_Kerr_221.ini
pyRing/config_files/Quickstart_configs/quick_gw150914_MMRDNP.ini
pyRingGW-2.7.0.dist-info/AUTHORS.md
pyRingGW-2.7.0.dist-info/LICENSE
pyRingGW-2.7.0.dist-info/METADATA
pyRingGW-2.7.0.dist-info/WHEEL
pyRingGW-2.7.0.dist-info/entry_points.txt
pyRingGW-2.7.0.dist-info/top_level.txt
pyRingGW-2.7.0.dist-info/RECORD
