Metadata-Version: 2.1
Name: pyRingGW
Version: 2.7.0
Summary: pyRing: Black hole ringdown data-analysis in time-domain
Home-page: https://git.ligo.org/lscsoft/pyring
Author: Gregorio Carullo, Walter Del Pozzo, John Veitch
Author-email: gregorio.carullo@ligo.org, walter.delpozzo@ligo.org, john.veitch@ligo.org
License: MIT
Project-URL: Bug Tracker, https://git.ligo.org/lscsoft/pyring/-/issues
Project-URL: Documentation, https://lscsoft.docs.ligo.org/pyring
Project-URL: Source Code, https://git.ligo.org/lscsoft/pyring
Platform: UNKNOWN
Classifier: License :: OSI Approved :: MIT License
Classifier: Operating System :: OS Independent
Classifier: Development Status :: 4 - Beta
Classifier: Programming Language :: Python :: 3
Classifier: Programming Language :: Python :: 3.8
Classifier: Programming Language :: Python :: 3.9
Classifier: Programming Language :: Python :: 3.10
Classifier: Programming Language :: Python :: 3.11
Requires-Python: >=3
Requires-Dist: corner
Requires-Dist: cpnest
Requires-Dist: cython
Requires-Dist: gwpy
Requires-Dist: h5py
Requires-Dist: lalsuite
Requires-Dist: matplotlib
Requires-Dist: numpy
Requires-Dist: pesummary
Requires-Dist: seaborn
Requires-Dist: scipy
Provides-Extra: docs
Requires-Dist: kotti-docs-theme ; extra == 'docs'
Requires-Dist: myst-parser ; extra == 'docs'
Requires-Dist: sphinx (==3.4.3) ; extra == 'docs'
Requires-Dist: sphinxcontrib-applehelp (==1.0.4) ; extra == 'docs'
Requires-Dist: sphinxcontrib-devhelp (==1.0.2) ; extra == 'docs'
Requires-Dist: sphinxcontrib-htmlhelp (==2.0.1) ; extra == 'docs'
Requires-Dist: sphinxcontrib-jsmath (==1.0.1) ; extra == 'docs'
Requires-Dist: sphinxcontrib-qthelp (==1.0.3) ; extra == 'docs'
Requires-Dist: sphinxcontrib-serializinghtml (==1.1.5) ; extra == 'docs'
Requires-Dist: sphinx-rtd-theme (==0.5.1) ; extra == 'docs'
Requires-Dist: readthedocs-sphinx-search (==0.1.0) ; extra == 'docs'
Requires-Dist: kotti-docs-theme (==0.2) ; extra == 'docs'
Requires-Dist: myst-parser (==0.17.2) ; extra == 'docs'
Requires-Dist: nbsphinx (==0.8.1) ; extra == 'docs'
Requires-Dist: jinja2 (==3.0.0) ; extra == 'docs'
